softadapt/__init__.py
softadapt/__version__.py
softadapt/algorithms/__init__.py
softadapt/algorithms/loss_weighted_variant.py
softadapt/algorithms/normalized_slopes_variant.py
softadapt/algorithms/original_variant.py
softadapt/base/__init__.py
softadapt/base/_softadapt_base_class.py
softadapt/callbacks/__init__.py
softadapt/callbacks/adaptive_loss.py
softadapt/constants/__init__.py
softadapt/utilities/__init__.py
softadapt/utilities/_finite_difference.py
softadapt-0.1.2.dist-info/METADATA
softadapt-0.1.2.dist-info/WHEEL
softadapt-0.1.2.dist-info/licenses/LICENSE.md
softadapt-0.1.2.dist-info/RECORD
