Metadata-Version: 2.4
Name: softadapt
Version: 0.1.2
Summary: SoftAdapt: Techniques for Adaptive Loss Weighting of Neural Networks with Multi-Part Loss Functions implemented in Keras
Project-URL: Homepage, https://github.com/logasja/SoftAdapt-Keras
Project-URL: Issues, https://github.com/logasja/SoftAdapt-Keras/issues
Author-email: "A. Ali Heydari" <aliheydari@ucdavis.edu>, Jacob Logas <jacob@logas.me>
Maintainer-email: Jacob Logas <jacob@logas.me>
License-Expression: GPL-3.0-or-later
License-File: LICENSE.md
Keywords: Adaptive-Weighting, Multi-Task-Nerual-Networks Optimization,Balancing PINNs Loss,Gradient-Descent-Weighting, Machine Learning,Physics-Informed Neural Networks
Classifier: Development Status :: 4 - Beta
Classifier: Intended Audience :: Science/Research
Classifier: Programming Language :: Python :: 3.10
Classifier: Programming Language :: Python :: 3.11
Classifier: Programming Language :: Python :: 3.12
Classifier: Programming Language :: Python :: 3.13
Classifier: Topic :: Scientific/Engineering :: Artificial Intelligence
Requires-Python: >=3.10
Requires-Dist: findiff
Requires-Dist: keras>=3.0.0
Requires-Dist: numpy
